<?xml version="1.0" encoding="UTF-8"?>
<people>
    <person>
        <id>1</id>
        <nombre>John Doe</nombre>
        <edad>30</edad>
        <email>johndoe@example.com</email>
    </person>
    <person>
        <id>2</id>
        <nombre>Jane Smith</nombre>
        <edad>25</edad>
        <email>janesmith@example.com</email>
    </person>
    <person>
        <id>3</id>
        <nombre>Michael Johnson</nombre>
        <edad>35</edad>
        <email>michaeljohnson@example.com</email>
    </person>
    <person>
        <id>4</id>
        <nombre>Emily Davis</nombre>
        <edad>28</edad>
        <email>emilydavis@example.com</email>
    </person>
    <person>
        <id>5</id>
        <nombre>other</nombre>
        <edad>99</edad>
        <email>other@email.com</email>
    </person>
</people>